insight_cli/__init__.py
insight_cli/main.py
insight_cli/api/__init__.py
insight_cli/api/create_repository_api.py
insight_cli/api/initialize_repository_api.py
insight_cli/api/query_repository_api.py
insight_cli/api/reinitialize_repository_api.py
insight_cli/api/uninitialize_repository_api.py
insight_cli/api/validate_repository_id_api.py
insight_cli/api/base/__init__.py
insight_cli/api/base/api.py
insight_cli/cli/__init__.py
insight_cli/cli/cli.py
insight_cli/commands/__init__.py
insight_cli/commands/initialize_command.py
insight_cli/commands/query_command.py
insight_cli/commands/status_command.py
insight_cli/commands/uninitialize_command.py
insight_cli/commands/version_command.py
insight_cli/commands/base/__init__.py
insight_cli/commands/base/command.py
insight_cli/commands/base/flag.py
insight_cli/config/__init__.py
insight_cli/config/config.py
insight_cli/repository/__init__.py
insight_cli/repository/authenticator.py
insight_cli/repository/file_tracker.py
insight_cli/repository/manager.py
insight_cli/repository/pattern_ignorer.py
insight_cli/repository/repository.py
insight_cli/utils/__init__.py
insight_cli/utils/chunked_file_encoder.py
insight_cli/utils/color.py
insight_cli/utils/directory.py
insight_cli/utils/file.py
insight_cli/utils/file_changes_detector.py
insight_cli/utils/file_chunkifier.py
insight_cli/utils/string_matcher.py
insight_cli-0.6.2.dist-info/LICENSE
insight_cli-0.6.2.dist-info/METADATA
insight_cli-0.6.2.dist-info/WHEEL
insight_cli-0.6.2.dist-info/entry_points.txt
insight_cli-0.6.2.dist-info/top_level.txt
insight_cli-0.6.2.dist-info/RECORD
