Metadata-Version: 2.1
Name: insight-cli
Version: 0.6.2
Requires-Python: >=3.10.0
License-File: LICENSE
Requires-Dist: colorama ==0.4.6
Requires-Dist: requests ==2.31.0
